{
    "type": "result",
    "timestamp": "2020-08-26T04:45:23Z",
    "ping": {
        "jitter": 10.476000000000001,
        "latency": 40.064999999999998
    },
    "download": {
        "bandwidth": 5608623,
        "bytes": 53941912,
        "elapsed": 9802
    },
    "upload": {
        "bandwidth": 604571,
        "bytes": 4587260,
        "elapsed": 7603
    },
    "packetLoss": 0,
    "isp": "Hudson Valley Wireless",
    "interface": {
        "internalIp": "192.168.1.18",
        "name": "wlp1s0",
        "macAddr": "64:5A:04:64:91:96",
        "isVpn": false,
        "externalIp": "208.71.250.245"
    },
    "server": {
        "id": 27111,
        "name": "MassiveMesh Networks",
        "location": "Troy, NY",
        "country": "United States",
        "host": "speedtest.massivemesh.com",
        "port": 8080,
        "ip": "38.104.52.188"
    },
    "result": {
        "id": "60178aa8-da4e-464d-8996-9f269364597a",
        "url": "https://www.speedtest.net/result/c/60178aa8-da4e-464d-8996-9f269364597a"
    }
}
