{
    "type": "result",
    "timestamp": "2020-09-14T08:45:21Z",
    "ping": {
        "jitter": 6.6289999999999996,
        "latency": 35.982999999999997
    },
    "download": {
        "bandwidth": 5556379,
        "bytes": 43988496,
        "elapsed": 8007
    },
    "upload": {
        "bandwidth": 605689,
        "bytes": 4845508,
        "elapsed": 8014
    },
    "packetLoss": 0,
    "isp": "Hudson Valley Wireless",
    "interface": {
        "internalIp": "192.168.1.18",
        "name": "wlp1s0",
        "macAddr": "64:5A:04:64:91:96",
        "isVpn": false,
        "externalIp": "208.71.250.247"
    },
    "server": {
        "id": 33195,
        "name": "Mid-Hudson Cablevision",
        "location": "Hudson, NY",
        "country": "United States",
        "host": "speedtest.mhcable.com",
        "port": 8080,
        "ip": "24.148.111.238"
    },
    "result": {
        "id": "7378d628-6497-4a7c-9397-d3a3a2c2bbe4",
        "url": "https://www.speedtest.net/result/c/7378d628-6497-4a7c-9397-d3a3a2c2bbe4"
    }
}
