{
    "type": "result",
    "timestamp": "2020-08-30T07:45:22Z",
    "ping": {
        "jitter": 10.488,
        "latency": 34.908999999999999
    },
    "download": {
        "bandwidth": 5646515,
        "bytes": 57671793,
        "elapsed": 10403
    },
    "upload": {
        "bandwidth": 610446,
        "bytes": 4477376,
        "elapsed": 7401
    },
    "packetLoss": 0.48309178743961351,
    "isp": "Hudson Valley Wireless",
    "interface": {
        "internalIp": "192.168.1.18",
        "name": "wlp1s0",
        "macAddr": "64:5A:04:64:91:96",
        "isVpn": false,
        "externalIp": "208.71.250.245"
    },
    "server": {
        "id": 5723,
        "name": "INOC Data Centers",
        "location": "Albany, NY",
        "country": "United States",
        "host": "speedtest.inoc.net",
        "port": 8080,
        "ip": "64.246.132.194"
    },
    "result": {
        "id": "faebc3eb-b52e-4bdb-9549-42fbe823e17d",
        "url": "https://www.speedtest.net/result/c/faebc3eb-b52e-4bdb-9549-42fbe823e17d"
    }
}
