{
    "type": "result",
    "timestamp": "2020-10-28T21:45:31Z",
    "ping": {
        "jitter": 10.789999999999999,
        "latency": 36.962000000000003
    },
    "download": {
        "bandwidth": 5421507,
        "bytes": 73762484,
        "elapsed": 14115
    },
    "upload": {
        "bandwidth": 599095,
        "bytes": 5092696,
        "elapsed": 8506
    },
    "packetLoss": 0,
    "isp": "Hudson Valley Wireless",
    "interface": {
        "internalIp": "192.168.1.18",
        "name": "wlp1s0",
        "macAddr": "64:5A:04:64:91:96",
        "isVpn": false,
        "externalIp": "208.71.250.204"
    },
    "server": {
        "id": 27111,
        "name": "MassiveMesh Networks",
        "location": "Troy, NY",
        "country": "United States",
        "host": "speedtest.massivemesh.com",
        "port": 8080,
        "ip": "38.104.52.188"
    },
    "result": {
        "id": "08453b8e-3cea-4df0-928d-708e9480396b",
        "url": "https://www.speedtest.net/result/c/08453b8e-3cea-4df0-928d-708e9480396b"
    }
}
