{
    "type": "result",
    "timestamp": "2020-11-18T01:45:30Z",
    "ping": {
        "jitter": 10.147,
        "latency": 28.582999999999998
    },
    "download": {
        "bandwidth": 741226,
        "bytes": 4650721,
        "elapsed": 6510
    },
    "upload": {
        "bandwidth": 500431,
        "bytes": 7108888,
        "elapsed": 14514
    },
    "packetLoss": 0,
    "isp": "Hudson Valley Wireless",
    "interface": {
        "internalIp": "192.168.1.18",
        "name": "wlp1s0",
        "macAddr": "64:5A:04:64:91:96",
        "isVpn": false,
        "externalIp": "208.71.250.66"
    },
    "server": {
        "id": 5723,
        "name": "INOC Data Centers",
        "location": "Albany, NY",
        "country": "United States",
        "host": "speedtest.inoc.net",
        "port": 8080,
        "ip": "64.246.132.194"
    },
    "result": {
        "id": "17dc1c3f-3d43-4c0e-96f3-1ba10300b1cc",
        "url": "https://www.speedtest.net/result/c/17dc1c3f-3d43-4c0e-96f3-1ba10300b1cc"
    }
}
