{
    "type": "result",
    "timestamp": "2020-11-18T07:45:29Z",
    "ping": {
        "jitter": 15.661,
        "latency": 30.681999999999999
    },
    "download": {
        "bandwidth": 5678008,
        "bytes": 80647277,
        "elapsed": 15003
    },
    "upload": {
        "bandwidth": 610346,
        "bytes": 3827481,
        "elapsed": 6300
    },
    "packetLoss": 0,
    "isp": "Hudson Valley Wireless",
    "interface": {
        "internalIp": "192.168.1.18",
        "name": "wlp1s0",
        "macAddr": "64:5A:04:64:91:96",
        "isVpn": false,
        "externalIp": "208.71.250.66"
    },
    "server": {
        "id": 5723,
        "name": "INOC Data Centers",
        "location": "Albany, NY",
        "country": "United States",
        "host": "speedtest.inoc.net",
        "port": 8080,
        "ip": "64.246.132.194"
    },
    "result": {
        "id": "1ecd8dda-8277-46c1-b4ef-3816cb553652",
        "url": "https://www.speedtest.net/result/c/1ecd8dda-8277-46c1-b4ef-3816cb553652"
    }
}
