{
    "type": "result",
    "timestamp": "2020-10-08T04:45:25Z",
    "ping": {
        "jitter": 14.375,
        "latency": 39.93
    },
    "download": {
        "bandwidth": 3732369,
        "bytes": 36328409,
        "elapsed": 9912
    },
    "upload": {
        "bandwidth": 519187,
        "bytes": 4332472,
        "elapsed": 8402
    },
    "packetLoss": 0,
    "isp": "Hudson Valley Wireless",
    "interface": {
        "internalIp": "192.168.1.18",
        "name": "wlp1s0",
        "macAddr": "64:5A:04:64:91:96",
        "isVpn": false,
        "externalIp": "208.71.250.208"
    },
    "server": {
        "id": 5723,
        "name": "INOC Data Centers",
        "location": "Albany, NY",
        "country": "United States",
        "host": "speedtest.inoc.net",
        "port": 8080,
        "ip": "64.246.132.194"
    },
    "result": {
        "id": "a819998b-2d89-490b-a967-d0b06f369909",
        "url": "https://www.speedtest.net/result/c/a819998b-2d89-490b-a967-d0b06f369909"
    }
}
