{
    "type": "result",
    "timestamp": "2020-10-01T07:45:24Z",
    "ping": {
        "jitter": 5.1539999999999999,
        "latency": 37.030999999999999
    },
    "download": {
        "bandwidth": 4810360,
        "bytes": 45956680,
        "elapsed": 10100
    },
    "upload": {
        "bandwidth": 475575,
        "bytes": 2720480,
        "elapsed": 5712
    },
    "packetLoss": 0,
    "isp": "Hudson Valley Wireless",
    "interface": {
        "internalIp": "192.168.1.18",
        "name": "wlp1s0",
        "macAddr": "64:5A:04:64:91:96",
        "isVpn": false,
        "externalIp": "208.71.250.247"
    },
    "server": {
        "id": 10292,
        "name": "TurnKey Internet, Inc.",
        "location": "Albany, NY",
        "country": "United States",
        "host": "speedtest.turnkeyinternet.net",
        "port": 8080,
        "ip": "173.198.219.78"
    },
    "result": {
        "id": "95b1387e-6100-4553-be5a-db76beb9808a",
        "url": "https://www.speedtest.net/result/c/95b1387e-6100-4553-be5a-db76beb9808a"
    }
}
