{
    "type": "result",
    "timestamp": "2020-08-17T04:45:27Z",
    "ping": {
        "jitter": 9.827,
        "latency": 39.831000000000003
    },
    "download": {
        "bandwidth": 5588208,
        "bytes": 79198165,
        "elapsed": 15004
    },
    "upload": {
        "bandwidth": 603164,
        "bytes": 3073677,
        "elapsed": 5103
    },
    "packetLoss": 0,
    "isp": "Hudson Valley Wireless",
    "interface": {
        "internalIp": "192.168.1.18",
        "name": "wlp1s0",
        "macAddr": "64:5A:04:64:91:96",
        "isVpn": false,
        "externalIp": "208.71.250.245"
    },
    "server": {
        "id": 5723,
        "name": "INOC Data Centers",
        "location": "Albany, NY",
        "country": "United States",
        "host": "speedtest.inoc.net",
        "port": 8080,
        "ip": "64.246.132.194"
    },
    "result": {
        "id": "18200131-4253-4df5-b45d-62095943e4af",
        "url": "https://www.speedtest.net/result/c/18200131-4253-4df5-b45d-62095943e4af"
    }
}
